gscraper/__init__.py
gscraper/core.py
gscraper/scraper.py
gscraper/utility.py
gscraper/web.py
gscraper-0.1.2.dist-info/METADATA
gscraper-0.1.2.dist-info/RECORD
gscraper-0.1.2.dist-info/WHEEL
gscraper-0.1.2.dist-info/top_level.txt
