Metadata-Version: 2.1
Name: gscraper
Version: 0.1.2
Summary: Automatically download images from google image search
Home-page: https://github.com/AlexNilsson/python-image-scraper
Author: Alexander Nilsson
Author-email: contact@alexnilsson.io
License: MIT
Keywords: web scraper google image images search automatic download
Platform: UNKNOWN
Requires-Dist: setuptools (>=28.8.0)
